msgraph_email/__init__.py
msgraph_email/_version.py
msgraph_email/auth/__init__.py
msgraph_email/auth/auth_service.py
msgraph_email/models/__init__.py
msgraph_email/models/auth_credentials.py
msgraph_email/models/email_attachment.py
msgraph_email/models/email_message.py
msgraph_email/services/__init__.py
msgraph_email/services/email_service.py
msgraph_email-2.0.2.dist-info/licenses/license
msgraph_email-2.0.2.dist-info/METADATA
msgraph_email-2.0.2.dist-info/WHEEL
msgraph_email-2.0.2.dist-info/top_level.txt
msgraph_email-2.0.2.dist-info/RECORD
