Metadata-Version: 2.4
Name: msgraph-email
Version: 2.0.2
Summary: Automate your emails using Microsoft Graph API
Home-page: https://github.com/pixelbyaj/msgraph-email
Author: Abhishek Joshi - PixelbyAJ
Author-email: pixelbyaj.dev@gmail.com
License: Apache
Project-URL: Documentation, https://github.com/pixelbyaj/msgraph-email#readme
Project-URL: Source, https://github.com/pixelbyaj/msgraph-email
Keywords: microsoft graph email outlook api
Classifier: License :: OSI Approved :: Apache Software License
Classifier: Programming Language :: Python :: 3.13
License-File: license
Requires-Dist: requests
Requires-Dist: msgraph-sdk
Requires-Dist: azure-identity
Dynamic: author
Dynamic: author-email
Dynamic: classifier
Dynamic: description
Dynamic: description-content-type
Dynamic: home-page
Dynamic: keywords
Dynamic: license
Dynamic: license-file
Dynamic: project-url
Dynamic: requires-dist
Dynamic: summary
